evalbench/__init__.py
evalbench/agents/__init__.py
evalbench/agents/interpretation.py
evalbench/agents/master.py
evalbench/agents/module_selection.py
evalbench/agents/recommendation.py
evalbench/agents/run_agent.py
evalbench/error_handling/__init__.py
evalbench/error_handling/custom_error.py
evalbench/error_handling/validation_helpers.py
evalbench/metrics/__init__.py
evalbench/metrics/evaluate_module.py
evalbench/metrics/custom/__init__.py
evalbench/metrics/custom/custom_metrics.py
evalbench/metrics/predefined/__init__.py
evalbench/metrics/predefined/contextual_generation.py
evalbench/metrics/predefined/query_alignment.py
evalbench/metrics/predefined/reference_based.py
evalbench/metrics/predefined/response_alignment.py
evalbench/metrics/predefined/response_quality.py
evalbench/metrics/predefined/retrieval.py
evalbench/runtime_setup/__init__.py
evalbench/runtime_setup/config.py
evalbench/runtime_setup/runtime.py
evalbench/utils/__init__.py
evalbench/utils/agent_helper.py
evalbench/utils/enum.py
evalbench/utils/metrics_helper.py
evalbench/utils/output_control.py
evalbench-1.0.1.dist-info/licenses/LICENSE.txt
evalbench-1.0.1.dist-info/METADATA
evalbench-1.0.1.dist-info/WHEEL
evalbench-1.0.1.dist-info/top_level.txt
evalbench-1.0.1.dist-info/RECORD
