Metadata-Version: 2.4
Name: evalbench
Version: 1.0.1
Summary: Lightweight, modular library for evaluating LLM outputs with built-in metrics, custom extensions, and agentic workflows.
Author-email: kotharisanjana <sanjanak98@gmail.com>
License: MIT
Requires-Python: >=3.8
License-File: LICENSE.txt
Requires-Dist: numpy
Requires-Dist: nltk
Requires-Dist: transformers
Requires-Dist: sentence-transformers
Requires-Dist: groq
Requires-Dist: rouge-score
Requires-Dist: bert-score
Provides-Extra: dev
Requires-Dist: pytest; extra == "dev"
Dynamic: license-file
